{
	"appId": "br.adv.skjuridico",
	"appName": "SK Jurídico",
	"webDir": "artifacts/assistente-juridico/dist/public",
	"server": {
		"androidScheme": "https",
		"hostname": "skjuridico.app"
	},
	"plugins": {
		"SplashScreen": {
			"launchShowDuration": 2500,
			"launchAutoHide": true,
			"backgroundColor": "#1a2b1a",
			"androidSplashResourceName": "splash",
			"showSpinner": false
		},
		"StatusBar": {
			"style": "Dark",
			"backgroundColor": "#1a2b1a",
			"overlaysWebView": false
		},
		"Keyboard": {
			"resize": "body",
			"resizeOnFullScreen": true,
			"style": "dark"
		},
		"LocalNotifications": {
			"smallIcon": "ic_stat_icon_config_sample",
			"iconColor": "#4a7c4a",
			"sound": "beep.wav"
		},
		"PushNotifications": {
			"presentationOptions": [
				"badge",
				"sound",
				"alert"
			]
		},
		"Network": {},
		"Storage": {},
		"Filesystem": {
			"directory": "Documents"
		},
		"Share": {},
		"Browser": {}
	},
	"android": {
		"minSdkVersion": 26,
		"targetSdkVersion": 34,
		"compileSdkVersion": 34,
		"useLegacyBridge": false
	},
	"ios": {
		"minVersion": "14.0",
		"limitsNavigationsToAppBoundDomains": true,
		"preferredContentMode": "mobile",
		"backgroundColor": "#1a2b1a",
		"scrollEnabled": true,
		"allowsLinkPreview": true,
		"handleApplicationNotifications": true
	}
}
